[{"name":"Bonelemo","ID":"73.17.20.200","Kode Pos":"91996"},{"name":"Sampeang","ID":"73.17.20.200","Kode Pos":"91996"},{"name":"Marinding","ID":"73.17.20.200","Kode Pos":"91996"},{"name":"Saronda","ID":"73.17.20.200","Kode Pos":"91996"},{"name":"Kadong-Kadong","ID":"73.17.20.200","Kode Pos":"91996"},{"name":"Tumbubara (Tumbu Barak)","ID":"73.17.20.200","Kode Pos":"91996"},{"name":"Tettekang (Tetekang)","ID":"73.17.20.200","Kode Pos":"91996"},{"name":"Bonelemo Utara","ID":"73.17.20.200","Kode Pos":"91996"},{"name":"Bonelemo Barat","ID":"73.17.20.200","Kode Pos":"91996"}]