[{"name":"Randa Empas","ID":"64.07.14.200","Kode Pos":"75778"},{"name":"Tuquk/Tukuq","ID":"64.07.14.200","Kode Pos":"75778"},{"name":"Tende","ID":"64.07.14.200","Kode Pos":"75778"},{"name":"Sambung","ID":"64.07.14.200","Kode Pos":"75778"},{"name":"Anan Jaya","ID":"64.07.14.200","Kode Pos":"75778"},{"name":"Jelmu Sibak","ID":"64.07.14.200","Kode Pos":"75778"},{"name":"Suakong","ID":"64.07.14.200","Kode Pos":"75778"},{"name":"Penarung","ID":"64.07.14.200","Kode Pos":"75778"},{"name":"Dilang Puti","ID":"64.07.14.200","Kode Pos":"75778"}]