[{"name":"Cupak","ID":"13.02.07.200","Kode Pos":"27365"},{"name":"Talang","ID":"13.02.07.200","Kode Pos":"27365"},{"name":"Koto Gadang Guguak","ID":"13.02.07.200","Kode Pos":"27365"},{"name":"Jawi Jawi","ID":"13.02.07.200","Kode Pos":"27365"},{"name":"Sungai Janiah","ID":"13.02.07.200","Kode Pos":"27365"},{"name":"Batang Barus","ID":"13.02.07.200","Kode Pos":"27365"},{"name":"Aie Batumbuak (Aia Batumbuak)","ID":"13.02.07.200","Kode Pos":"27365"},{"name":"Koto Gaek Guguk","ID":"13.02.07.200","Kode Pos":"27365"}]