[{"name":"Ikebo (Moanemani)","ID":"94.06.01.200","Kode Pos":"98882"},{"name":"Mauwa","ID":"94.06.01.200","Kode Pos":"98882"},{"name":"Ekemanida (Ekemenida)","ID":"94.06.01.200","Kode Pos":"98882"},{"name":"Bukapa (Bugapa)","ID":"94.06.01.200","Kode Pos":"98882"},{"name":"Kimipugi (Kimupugi)","ID":"94.06.01.200","Kode Pos":"98882"},{"name":"Dikiyouwo (Dikiyouwa / Dikiyouma / Tokapo)","ID":"94.06.01.200","Kode Pos":"98882"},{"name":"Idakotu","ID":"94.06.01.200","Kode Pos":"98882"},{"name":"Putapa (Uputapa)","ID":"94.06.01.200","Kode Pos":"98882"}]