[{"name":"Kedamaian","ID":"18.71.18.100","Kode Pos":"35122"},{"name":"Bumi Kedamaian","ID":"18.71.18.100","Kode Pos":"35122"},{"name":"Tanjungagung Raya (Tanjung Agung Raya)","ID":"18.71.18.100","Kode Pos":"35129"},{"name":"Tanjungbaru (Tanjung Baru)","ID":"18.71.18.100","Kode Pos":"35133"},{"name":"Kalibalau Kencana (Kali Balok / Balau Kencana)","ID":"18.71.18.100","Kode Pos":"35132"},{"name":"Tanjungraya (Tanjung Raya)","ID":"18.71.18.100","Kode Pos":"35128"},{"name":"Tanjunggading (Tanjung Gading)","ID":"18.71.18.100","Kode Pos":"35128"}]