[{"name":"Udagaga","ID":"92.04.21.200","Kode Pos":"98224"},{"name":"Kayubiro","ID":"92.04.21.200","Kode Pos":"98224"},{"name":"Adona","ID":"92.04.21.200","Kode Pos":"98224"},{"name":"Benawa II","ID":"92.04.21.200","Kode Pos":"98224"},{"name":"Atori","ID":"92.04.21.200","Kode Pos":"98224"},{"name":"Kamundan Satu","ID":"92.04.21.200","Kode Pos":"98224"},{"name":"Karirif","ID":"92.04.21.200","Kode Pos":"98224"},{"name":"Bubuko","ID":"92.04.21.200","Kode Pos":"98224"},{"name":"Kamundan Dua","ID":"92.04.21.200","Kode Pos":"98224"}]