[{"name":"Ujung Tanjung I (satu)","ID":"17.07.08.200","Kode Pos":"39267"},{"name":"Muning Agung","ID":"17.07.08.200","Kode Pos":"39267"},{"name":"Ujung Tanjung II (dua)","ID":"17.07.08.200","Kode Pos":"39267"},{"name":"Ujung Tanjung III (tiga)","ID":"17.07.08.200","Kode Pos":"39267"},{"name":"Magelang Baru","ID":"17.07.08.200","Kode Pos":"39267"},{"name":"Lemeu Pit","ID":"17.07.08.200","Kode Pos":"39267"},{"name":"Tabeak Kauk","ID":"17.07.08.200","Kode Pos":"39267"},{"name":"Tabeak Dipoa","ID":"17.07.08.200","Kode Pos":"39267"},{"name":"Suka Bumi","ID":"17.07.08.200","Kode Pos":"39267"}]