[{"name":"Pining (Pinding)","ID":"11.13.05.200","Kode Pos":"24659"},{"name":"Pertik","ID":"11.13.05.200","Kode Pos":"24659"},{"name":"Ekan","ID":"11.13.05.200","Kode Pos":"24659"},{"name":"Uring","ID":"11.13.05.200","Kode Pos":"24659"},{"name":"Gajah","ID":"11.13.05.200","Kode Pos":"24659"},{"name":"Pintu Rime","ID":"11.13.05.200","Kode Pos":"24659"},{"name":"Pepelah","ID":"11.13.05.200","Kode Pos":"24659"},{"name":"Pasir Putih","ID":"11.13.05.200","Kode Pos":"24659"},{"name":"Lesten","ID":"11.13.05.200","Kode Pos":"24659"}]