[{"name":"Silosung","ID":"12.02.07.200","Kode Pos":"22466"},{"name":"Dolok Sanggul","ID":"12.02.07.200","Kode Pos":"22466"},{"name":"Simangumban Jae","ID":"12.02.07.200","Kode Pos":"22466"},{"name":"Aek Nabara","ID":"12.02.07.200","Kode Pos":"22466"},{"name":"Dolok Saut","ID":"12.02.07.200","Kode Pos":"22466"},{"name":"Simangumban Julu","ID":"12.02.07.200","Kode Pos":"22466"},{"name":"Lobu Sihim","ID":"12.02.07.200","Kode Pos":"22466"},{"name":"Pardomuan","ID":"12.02.07.200","Kode Pos":"22466"}]