[{"name":"Setanggor","ID":"52.03.06.200","Kode Pos":"83652"},{"name":"Jantuk","ID":"52.03.06.200","Kode Pos":"83652"},{"name":"Padamara","ID":"52.03.06.200","Kode Pos":"83652"},{"name":"Dasan Lekong","ID":"52.03.06.200","Kode Pos":"83652"},{"name":"Sukamulia","ID":"52.03.06.200","Kode Pos":"83652"},{"name":"Paok Pampang","ID":"52.03.06.200","Kode Pos":"83652"},{"name":"Sukamulia Timur","ID":"52.03.06.200","Kode Pos":"83652"},{"name":"Nyiur Tebel","ID":"52.03.06.200","Kode Pos":"83652"},{"name":"Setanggor Selatan","ID":"52.03.06.200","Kode Pos":"83652"}]