[{"name":"Darul Aman","ID":"11.03.01"},{"name":"Julok","ID":"11.03.02"},{"name":"Idi Rayeuk","ID":"11.03.03"},{"name":"Birem Bayeun","ID":"11.03.04"},{"name":"Serbajadi","ID":"11.03.05"},{"name":"Nurussalam","ID":"11.03.06"},{"name":"Peureulak","ID":"11.03.07"},{"name":"Rantau Selamat","ID":"11.03.08"},{"name":"Simpang Ulim","ID":"11.03.09"},{"name":"Rantau Peureulak (Ranto Peureulak)","ID":"11.03.10"},{"name":"Pante Bidari","ID":"11.03.11"},{"name":"Madat","ID":"11.03.12"},{"name":"Indra Makmu (Indra Makmur)","ID":"11.03.13"},{"name":"Idi Tunong","ID":"11.03.14"},{"name":"Banda Alam","ID":"11.03.15"},{"name":"Peudawa","ID":"11.03.16"},{"name":"Peureulak Timur","ID":"11.03.17"},{"name":"Peureulak Barat","ID":"11.03.18"},{"name":"Sungai Raya","ID":"11.03.19"},{"name":"Simpang Jernih","ID":"11.03.20"},{"name":"Darul Ihsan (Iksan)","ID":"11.03.21"},{"name":"Darul Falah","ID":"11.03.22"},{"name":"Idi Timur","ID":"11.03.23"},{"name":"Peunaron","ID":"11.03.24"}]