[{"name":"Wamena","ID":"95.01.01"},{"name":"Kurulu","ID":"95.01.02"},{"name":"Asologaima","ID":"95.01.03"},{"name":"Hubikosi","ID":"95.01.04"},{"name":"Bolakme","ID":"95.01.05"},{"name":"Walelagama","ID":"95.01.06"},{"name":"Musatfak","ID":"95.01.07"},{"name":"Wolo","ID":"95.01.08"},{"name":"Asolokobal","ID":"95.01.09"},{"name":"Pelebaga","ID":"95.01.10"},{"name":"Yalengga","ID":"95.01.11"},{"name":"Trikora","ID":"95.01.12"},{"name":"Napua","ID":"95.01.13"},{"name":"Walaik","ID":"95.01.14"},{"name":"Wouma","ID":"95.01.15"},{"name":"Hubikiak","ID":"95.01.16"},{"name":"Ibele","ID":"95.01.17"},{"name":"Taelarek","ID":"95.01.18"},{"name":"Itlay Hisage","ID":"95.01.19"},{"name":"Siepkosi","ID":"95.01.20"},{"name":"Usilimo","ID":"95.01.21"},{"name":"Wita Waya","ID":"95.01.22"},{"name":"Libarek","ID":"95.01.23"},{"name":"Wadangku","ID":"95.01.24"},{"name":"Pisugi","ID":"95.01.25"},{"name":"Koragi","ID":"95.01.26"},{"name":"Tagime","ID":"95.01.27"},{"name":"Molagalome","ID":"95.01.28"},{"name":"Tagineri","ID":"95.01.29"},{"name":"Silo Karno Doga","ID":"95.01.30"},{"name":"Piramid","ID":"95.01.31"},{"name":"Muliama","ID":"95.01.32"},{"name":"Bugi","ID":"95.01.33"},{"name":"Bpiri","ID":"95.01.34"},{"name":"Welesi","ID":"95.01.35"},{"name":"Asotipo","ID":"95.01.36"},{"name":"Maima","ID":"95.01.37"},{"name":"Popugoba","ID":"95.01.38"},{"name":"Wame","ID":"95.01.39"},{"name":"Wesaput","ID":"95.01.40"}]